unbihexium/__init__.py
unbihexium/_version.py
unbihexium/py.typed
unbihexium/ai/__init__.py
unbihexium/ai/detection.py
unbihexium/ai/segmentation.py
unbihexium/ai/super_resolution.py
unbihexium/ai/change_detection/__init__.py
unbihexium/ai/change_detection/siamese.py
unbihexium/ai/models/__init__.py
unbihexium/ai/models/fpn.py
unbihexium/ai/models/heads.py
unbihexium/ai/models/mlp.py
unbihexium/ai/models/registry.py
unbihexium/ai/models/resnet.py
unbihexium/ai/models/unet.py
unbihexium/ai/super_resolution/__init__.py
unbihexium/ai/super_resolution/srcnn.py
unbihexium/ai/synthesis/__init__.py
unbihexium/ai/synthesis/augmenter.py
unbihexium/analysis/__init__.py
unbihexium/analysis/network.py
unbihexium/analysis/suitability.py
unbihexium/analysis/zonal.py
unbihexium/analysis/network/__init__.py
unbihexium/analysis/network/a_star.py
unbihexium/cli/__init__.py
unbihexium/cli/main.py
unbihexium/config/__init__.py
unbihexium/core/__init__.py
unbihexium/core/evidence.py
unbihexium/core/index.py
unbihexium/core/model.py
unbihexium/core/pipeline.py
unbihexium/core/product.py
unbihexium/core/raster.py
unbihexium/core/scene.py
unbihexium/core/sensor.py
unbihexium/core/tile.py
unbihexium/core/vector.py
unbihexium/geostat/__init__.py
unbihexium/geostat/kriging.py
unbihexium/geostat/spatial.py
unbihexium/geostat/variogram.py
unbihexium/indices/__init__.py
unbihexium/io/__init__.py
unbihexium/io/geojson.py
unbihexium/io/geotiff.py
unbihexium/io/parquet.py
unbihexium/io/stac.py
unbihexium/io/zarr_io.py
unbihexium/metrics/__init__.py
unbihexium/postprocessing/__init__.py
unbihexium/preprocessing/__init__.py
unbihexium/registry/__init__.py
unbihexium/registry/capabilities.py
unbihexium/registry/models.py
unbihexium/registry/pipelines.py
unbihexium/sar/__init__.py
unbihexium/sar/amplitude.py
unbihexium/sar/interferometry.py
unbihexium/sar/polarimetry.py
unbihexium/serving/__init__.py
unbihexium/serving/app.py
unbihexium/serving/inference.py
unbihexium/serving/schemas.py
unbihexium-1.0.1.dist-info/METADATA
unbihexium-1.0.1.dist-info/WHEEL
unbihexium-1.0.1.dist-info/entry_points.txt
unbihexium-1.0.1.dist-info/licenses/LICENSE.txt
unbihexium-1.0.1.dist-info/licenses/NOTICE
unbihexium-1.0.1.dist-info/licenses/NOTICE.md
unbihexium-1.0.1.dist-info/RECORD
