Metadata-Version: 2.4
Name: unbihexium
Version: 1.0.1
Summary: Production-grade Earth Observation, Geospatial, Remote Sensing, and SAR Python library
Project-URL: Homepage, https://unbihexium.org
Project-URL: Documentation, https://unbihexium.org/docs
Project-URL: Repository, https://github.com/unbihexium-oss/unbihexium
Project-URL: Issues, https://github.com/unbihexium-oss/unbihexium/issues
Project-URL: Changelog, https://github.com/unbihexium-oss/unbihexium/blob/main/CHANGELOG.md
Author-email: Unbihexium OSS Foundation <opensource@unbihexium.org>
Maintainer-email: Unbihexium OSS Foundation <opensource@unbihexium.org>
License: Apache-2.0
License-File: LICENSE.txt
License-File: NOTICE
License-File: NOTICE.md
Keywords: agriculture,change-detection,deep-learning,earth-observation,environmental-monitoring,flood-mapping,geospatial,gis,machine-learning,object-detection,remote-sensing,sar,satellite-imagery,segmentation,urban-planning
Classifier: Development Status :: 5 - Production/Stable
Classifier: Intended Audience :: Developers
Classifier: Intended Audience :: Science/Research
Classifier: License :: OSI Approved :: Apache Software License
Classifier: Operating System :: OS Independent
Classifier: Programming Language :: Python :: 3
Classifier: Programming Language :: Python :: 3.10
Classifier: Programming Language :: Python :: 3.11
Classifier: Programming Language :: Python :: 3.12
Classifier: Topic :: Scientific/Engineering :: Artificial Intelligence
Classifier: Topic :: Scientific/Engineering :: GIS
Classifier: Topic :: Scientific/Engineering :: Image Processing
Classifier: Typing :: Typed
Requires-Python: >=3.10
Requires-Dist: click>=8.1.0
Requires-Dist: geopandas>=0.14.0
Requires-Dist: numpy>=1.24.0
Requires-Dist: pillow>=10.0.0
Requires-Dist: pydantic>=2.5.0
Requires-Dist: pyproj>=3.6.0
Requires-Dist: pyyaml>=6.0.0
Requires-Dist: rasterio>=1.3.0
Requires-Dist: requests>=2.31.0
Requires-Dist: rich>=13.0.0
Requires-Dist: scikit-image>=0.22.0
Requires-Dist: scikit-learn>=1.3.0
Requires-Dist: scipy>=1.11.0
Requires-Dist: shapely>=2.0.0
Requires-Dist: tqdm>=4.66.0
Provides-Extra: all
Requires-Dist: bandit>=1.7.0; extra == 'all'
Requires-Dist: dask[complete]>=2024.1.0; extra == 'all'
Requires-Dist: h5py>=3.10.0; extra == 'all'
Requires-Dist: mkdocs-material>=9.5.0; extra == 'all'
Requires-Dist: mkdocs>=1.5.0; extra == 'all'
Requires-Dist: mkdocstrings[python]>=0.24.0; extra == 'all'
Requires-Dist: netcdf4>=1.6.0; extra == 'all'
Requires-Dist: pip-audit>=2.6.0; extra == 'all'
Requires-Dist: pre-commit>=3.6.0; extra == 'all'
Requires-Dist: pyarrow>=14.0.0; extra == 'all'
Requires-Dist: pymdown-extensions>=10.0.0; extra == 'all'
Requires-Dist: pyright>=1.1.340; extra == 'all'
Requires-Dist: pystac-client>=0.7.0; extra == 'all'
Requires-Dist: pystac>=1.9.0; extra == 'all'
Requires-Dist: pytest-cov>=4.1.0; extra == 'all'
Requires-Dist: pytest-xdist>=3.5.0; extra == 'all'
Requires-Dist: pytest>=7.4.0; extra == 'all'
Requires-Dist: ray>=2.9.0; extra == 'all'
Requires-Dist: ruff>=0.1.0; extra == 'all'
Requires-Dist: torch>=2.1.0; extra == 'all'
Requires-Dist: torchvision>=0.16.0; extra == 'all'
Requires-Dist: zarr>=2.16.0; extra == 'all'
Provides-Extra: dask
Requires-Dist: dask[complete]>=2024.1.0; extra == 'dask'
Provides-Extra: dev
Requires-Dist: bandit>=1.7.0; extra == 'dev'
Requires-Dist: pip-audit>=2.6.0; extra == 'dev'
Requires-Dist: pre-commit>=3.6.0; extra == 'dev'
Requires-Dist: pyright>=1.1.340; extra == 'dev'
Requires-Dist: pytest-cov>=4.1.0; extra == 'dev'
Requires-Dist: pytest-xdist>=3.5.0; extra == 'dev'
Requires-Dist: pytest>=7.4.0; extra == 'dev'
Requires-Dist: ruff>=0.1.0; extra == 'dev'
Provides-Extra: docs
Requires-Dist: mkdocs-material>=9.5.0; extra == 'docs'
Requires-Dist: mkdocs>=1.5.0; extra == 'docs'
Requires-Dist: mkdocstrings[python]>=0.24.0; extra == 'docs'
Requires-Dist: pymdown-extensions>=10.0.0; extra == 'docs'
Provides-Extra: gpu
Requires-Dist: cupy-cuda12x>=12.0.0; extra == 'gpu'
Requires-Dist: torch>=2.1.0; extra == 'gpu'
Requires-Dist: torchvision>=0.16.0; extra == 'gpu'
Provides-Extra: netcdf
Requires-Dist: h5py>=3.10.0; extra == 'netcdf'
Requires-Dist: netcdf4>=1.6.0; extra == 'netcdf'
Provides-Extra: parquet
Requires-Dist: pyarrow>=14.0.0; extra == 'parquet'
Provides-Extra: ray
Requires-Dist: ray>=2.9.0; extra == 'ray'
Provides-Extra: stac
Requires-Dist: pystac-client>=0.7.0; extra == 'stac'
Requires-Dist: pystac>=1.9.0; extra == 'stac'
Provides-Extra: torch
Requires-Dist: torch>=2.1.0; extra == 'torch'
Requires-Dist: torchvision>=0.16.0; extra == 'torch'
Provides-Extra: zarr
Requires-Dist: zarr>=2.16.0; extra == 'zarr'
